{
    "initial_group_count": 75,
    "filtered_group_count": 11,
    "step_1_time": 13.31638503074646,
    "step_2_time": 31.434608936309814,
    "solution_details": [
        {
            "group": "{'GINI': 'Medium'}",
            "details": {
                "size": 14429,
                "covered": [
                    "Australia",
                    "Germany",
                    "Italy",
                    "Poland",
                    "Spain",
                    "France",
                    "Canada",
                    "United Kingdom"
                ],
                "t_h": {
                    "Age": "35 - 44 years old"
                },
                "cate_h": 34809.474602845294,
                "t_l": {
                    "Age": "18 - 24 years old"
                },
                "cate_l": -43843.58799401115,
                "explainability": 78653.06259685644
            }
        },
        {
            "group": "{'Continent': 'EU'}",
            "details": {
                "size": 15921,
                "covered": [
                    "Sweden",
                    "Ukraine",
                    "Belgium",
                    "Russian Federation",
                    "Germany",
                    "Netherlands",
                    "Italy",
                    "Austria",
                    "Poland",
                    "Spain",
                    "France",
                    "United Kingdom",
                    "Switzerland"
                ],
                "t_h": {
                    "Age": "35 - 44 years old"
                },
                "cate_h": 37826.77730048106,
                "t_l": {
                    "Age": "18 - 24 years old"
                },
                "cate_l": -46248.73279141989,
                "explainability": 84075.51009190094
            }
        },
        {
            "group": "{'GINI': 'High'}",
            "details": {
                "size": 20653,
                "covered": [
                    "Ukraine",
                    "Turkey",
                    "Russian Federation",
                    "Brazil",
                    "India",
                    "United States",
                    "Israel"
                ],
                "t_h": {
                    "Age": "35 - 44 years old",
                    "RaceEthnicity": "White or of European descent"
                },
                "cate_h": 41501.0813418981,
                "t_l": {
                    "RaceEthnicity": "South Asian"
                },
                "cate_l": -58763.74328511446,
                "explainability": 100264.82462701257
            }
        }
    ],
    "overall_explainability": 262993.3973157699,
    "coverage": 1.0,
    "total_groups": 20,
    "total_groups_in_aggregated_view": 20,
    "step_3_time": 0.03894805908203125,
    "total_time": 44.789942026138306
}